[[0,["start",{"collapsed":false,"xcor":101.50571820752957,"ycor":-35.94506003535347,"heading":220,"color":0,"shade":50,"pensize":5,"grey":100}],486,84,[null,1,null]],[1,["penup",{}],500,125,[0,3]],[2,["pendown",{}],500,220,[3,6]],[3,["setxy",{}],500,157,[1,4,5,2]],[4,["number",{"value":159}],574,157,[3]],[5,["number",{"value":0}],574,189,[3]],[6,["arc",{}],500,252,[2,7,8,22]],[7,["number",{"value":360}],574,252,[6]],[8,["number",{"value":211}],574,284,[6]],[9,["start",{"collapsed":false,"xcor":0,"ycor":0,"heading":0,"color":10,"shade":50,"pensize":5,"grey":100}],-13,129,[null,null,null]],[10,["start",{"collapsed":false,"xcor":0,"ycor":0,"heading":0,"color":20,"shade":50,"pensize":5,"grey":100}],224,95,[null,11,null]],[11,["penup",{}],238,136,[10,12]],[12,["setxy",{}],238,168,[11,13,14,15]],[13,["number",{"value":-249}],312,168,[12]],[14,["number",{"value":81}],312,200,[12]],[15,["pendown",{}],238,231,[12,16]],[16,["arc",{}],238,263,[15,17,18,null]],[17,["number",{"value":360}],312,263,[16]],[18,["number",{"value":211}],312,295,[16]],[19,["setxy",{}],500,347,[22,20,21,23]],[20,["number",{"value":240}],574,347,[19]],[21,["number",{"value":0}],574,379,[19]],[22,["penup",{}],500,315,[6,19]],[23,["pendown",{}],500,410,[19,24]],[24,["repeat",{}],500,442,[23,25,29,null]],[25,["number",{"value":360}],572,442,[24]],[26,["setcolor",{}],103,389,[null,27,null]],[27,["number",{"value":0}],190,389,[26]],[28,["penup",{}],514,570,[32,null]],[29,["pendown",{}],514,474,[24,30]],[30,["forward",{}],514,506,[29,31,32]],[31,["number",{"value":1}],594,506,[30]],[32,["right",{}],514,538,[30,33,28]],[33,["number",{"value":1}],588,538,[32]]]